src/__init__.py
src/functionTest.py
getFunctionTest-0.0.5.dist-info/METADATA
getFunctionTest-0.0.5.dist-info/WHEEL
getFunctionTest-0.0.5.dist-info/entry_points.txt
getFunctionTest-0.0.5.dist-info/top_level.txt
getFunctionTest-0.0.5.dist-info/RECORD
