Metadata-Version: 2.1
Name: getFunctionTest
Version: 0.0.5
Summary: Test buat library python
Home-page: UNKNOWN
Author: sinbad
Author-email: email@gmail.com
License: MIT
Platform: UNKNOWN
